dls_slurmjob_api/__init__.py
dls_slurmjob_api/aiohttp_client.py
dls_slurmjob_api/constants.py
dls_slurmjob_api/exceptions.py
dls_slurmjob_api/interfaces/client.py
dls_slurmjob_api/models/job_summary_model.py
dls_slurmjob_api/models/openapi/__init__.py
dls_slurmjob_api/models/openapi/openapi.json
dls_slurmjob_api/models/openapi/dbv0/__init__.py
dls_slurmjob_api/models/openapi/dbv0/field_0.py
dls_slurmjob_api/models/openapi/v0/__init__.py
dls_slurmjob_api/models/openapi/v0/field_0.py
dls_slurmjob_api/restds/__init__.py
dls_slurmjob_api/restds/aiohttp.py
dls_slurmjob_api/restds/constants.py
dls_slurmjob_api/restds/context.py
dls_slurmjob_api/restds/dummy.py
dls_slurmjob_api/restds/restds.py
dls_slurmjob_cli/__init__.py
dls_slurmjob_cli/main.py
dls_slurmjob_cli/version.py
dls_slurmjob_cli/subcommands/__init__.py
dls_slurmjob_cli/subcommands/base.py
dls_slurmjob_cli/subcommands/query_jobs.py
dls_slurmjob_cli/subcommands/submit_job.py
dls_slurmjob_lib/__init__.py
dls_slurmjob_lib/__main__.py
dls_slurmjob_lib/_version.py
dls_slurmjob_lib/envvar.py
dls_slurmjob_lib/version.py
dls_slurmjob-1.0.3.dist-info/LICENSE
dls_slurmjob-1.0.3.dist-info/METADATA
dls_slurmjob-1.0.3.dist-info/WHEEL
dls_slurmjob-1.0.3.dist-info/entry_points.txt
dls_slurmjob-1.0.3.dist-info/top_level.txt
dls_slurmjob-1.0.3.dist-info/RECORD
