Metadata-Version: 2.1
Name: dls-slurmjob
Version: 1.0.3
Summary: Simplified job submit and status using Slurm REST.
Author-email: David Erb <david.erb@diamond.ac.uk>
License: Apache License
Project-URL: GitLab, https://gitlab.diamond.ac.uk/kbp43231/dls-slurmjob
Classifier: Development Status :: 3 - Alpha
Classifier: License :: OSI Approved :: Apache Software License
Classifier: Programming Language :: Python :: 3.10
Requires-Python: >=3.10
License-File: LICENSE
Requires-Dist: dls-mainiac
Requires-Dist: dls-multiconf
Requires-Dist: dls-utilpack
Requires-Dist: aiohttp
Requires-Dist: pydantic
Provides-Extra: dev
Requires-Dist: black (==22.12.0) ; extra == 'dev'
Requires-Dist: mypy ; extra == 'dev'
Requires-Dist: flake8-isort ; extra == 'dev'
Requires-Dist: Flake8-pyproject ; extra == 'dev'
Requires-Dist: pipdeptree ; extra == 'dev'
Requires-Dist: pre-commit ; extra == 'dev'
Requires-Dist: pytest-cov ; extra == 'dev'
Requires-Dist: pydocstyle[toml] ; extra == 'dev'
Requires-Dist: tox-direct ; extra == 'dev'
Requires-Dist: types-mock ; extra == 'dev'
Requires-Dist: types-PyYAML ; extra == 'dev'
Provides-Extra: docs
Requires-Dist: pydata-sphinx-theme (>=0.12) ; extra == 'docs'
Requires-Dist: sphinx-argparse ; extra == 'docs'
Requires-Dist: sphinx-autobuild ; extra == 'docs'
Requires-Dist: sphinx-copybutton ; extra == 'docs'
Requires-Dist: sphinx-design ; extra == 'docs'
Requires-Dist: tox-direct ; extra == 'docs'
Requires-Dist: nbsphinx ; extra == 'docs'
Requires-Dist: pandoc ; extra == 'docs'
Requires-Dist: ipykernel ; extra == 'docs'
Requires-Dist: h5py ; extra == 'docs'
Requires-Dist: matplotlib ; extra == 'docs'
